LICENSE
README.md
setup.cfg
setup.py
zmpe/__init__.py
zmpe/version.py
zmpe/zm.py
zmpe/zm_lib.py
zmpe.egg-info/PKG-INFO
zmpe.egg-info/SOURCES.txt
zmpe.egg-info/dependency_links.txt
zmpe.egg-info/requires.txt
zmpe.egg-info/top_level.txt