Metadata-Version: 2.1
Name: zmpe
Version: 1.0.4
Summary: The program controls the execution of any programs, scripts or commands OS and sends the execution result to zabbix, and in case of an execution error, it additionally can notify via telegram.
Home-page: https://github.com/MinistrBob/zabbix-monitoring-programs-execution.git
Author: Dmitry Bobrovsky
Author-email: ministrbob777@gmail.com
Classifier: Development Status :: 5 - Production/Stable
Classifier: License :: OSI Approved :: MIT License
Classifier: Programming Language :: Python :: 3
Classifier: Topic :: System :: Monitoring
License-File: LICENSE
